[
  {
    "ContainingType": "Authorize.API.Controllers.AuthorizeController",
    "Method": "AcceptEmailConfirmation",
    "RelativePath": "api/Authorize/AcceptEmailConfirmation",
    "HttpMethod": "POST",
    "IsController": true,
    "Order": 0,
    "Parameters": [
      {
        "Name": "UserEmail",
        "Type": "System.String",
        "IsRequired": false
      },
      {
        "Name": "Code",
        "Type": "System.String",
        "IsRequired": false
      }
    ],
    "ReturnTypes": []
  },
  {
    "ContainingType": "Authorize.API.Controllers.AuthorizeController",
    "Method": "ActiveUser",
    "RelativePath": "api/Authorize/ActiveUser",
    "HttpMethod": "PATCH",
    "IsController": true,
    "Order": 0,
    "Parameters": [
      {
        "Name": "request",
        "Type": "Authorize.Application.Commands.User.ActiveUsers.ActiveUsersCommand",
        "IsRequired": true
      }
    ],
    "ReturnTypes": []
  },
  {
    "ContainingType": "Authorize.API.Controllers.AuthorizeController",
    "Method": "ConfirmEmail",
    "RelativePath": "api/Authorize/ConfirmEmail",
    "HttpMethod": "POST",
    "IsController": true,
    "Order": 0,
    "Parameters": [
      {
        "Name": "request",
        "Type": "Authorize.Application.Commands.User.ConfirmUserEmail.ConfirmUserEmailCommand",
        "IsRequired": true
      }
    ],
    "ReturnTypes": []
  },
  {
    "ContainingType": "Authorize.API.Controllers.AuthorizeController",
    "Method": "Login",
    "RelativePath": "api/Authorize/Login",
    "HttpMethod": "GET",
    "IsController": true,
    "Order": 0,
    "Parameters": [
      {
        "Name": "Email",
        "Type": "System.String",
        "IsRequired": false
      },
      {
        "Name": "Password",
        "Type": "System.String",
        "IsRequired": false
      }
    ],
    "ReturnTypes": []
  },
  {
    "ContainingType": "Authorize.API.Controllers.AuthorizeController",
    "Method": "Register",
    "RelativePath": "api/Authorize/Register",
    "HttpMethod": "POST",
    "IsController": true,
    "Order": 0,
    "Parameters": [
      {
        "Name": "request",
        "Type": "Authorize.Application.Commands.User.RegisterUser.RegisterUserCommand",
        "IsRequired": true
      }
    ],
    "ReturnTypes": []
  }
]